txtaugsrc/__init__.py
txtaugsrc/baidu_trans.py
txtaugsrc/config.py
txtaugsrc/txtaug.py
txtaug-0.0.1.dist-info/METADATA
txtaug-0.0.1.dist-info/WHEEL
txtaug-0.0.1.dist-info/entry_points.txt
txtaug-0.0.1.dist-info/top_level.txt
txtaug-0.0.1.dist-info/RECORD
